pyenergyaspects/__init__.py
pyenergyaspects/eaapi.py
tests/__init__.py
tests/test_eaapi.py
pyenergyaspects-0.0.3.dist-info/METADATA
pyenergyaspects-0.0.3.dist-info/WHEEL
pyenergyaspects-0.0.3.dist-info/top_level.txt
pyenergyaspects-0.0.3.dist-info/RECORD
