Metadata-Version: 2.1
Name: pyenergyaspects
Version: 0.0.3
Summary: Wrapper around Energy Aspects API
Home-page: https://github.com/aeorxc/pyenergyaspects
Author: aeorxc
License: UNKNOWN
Project-URL: Source, https://github.com/aeorxc/pyenergyaspects
Platform: UNKNOWN
Classifier: Programming Language :: Python :: 3
Classifier: License :: OSI Approved :: MIT License
Classifier: Operating System :: OS Independent
Requires-Python: >=3.8
Requires-Dist: pandas
Requires-Dist: requests
